{
  "sections": {
    "custom_liquid_h6prJp": {
      "type": "custom-liquid",
      "settings": {
        "custom_liquid": "",
        "color_scheme": "",
        "padding_top": 40,
        "padding_bottom": 0
      }
    },
    "hotspot_section_4EmjLw": {
      "type": "hotspot-section",
      "blocks": {
        "hotspot_HEJHDV": {
          "type": "hotspot",
          "settings": {
            "product": "ruffle-power-pareo-pre-order",
            "variant_img": "shopify:\/\/shop_images\/CPB_S24_PetitPalmRed_Pareo_Gauze_049ce845-e65c-43fe-aff3-eced37d65d38.jpg",
            "hovertext": false,
            "tooltip_text": "Hover Text Here",
            "top": 18,
            "left": 52
          }
        },
        "hotspot_6JRnwK": {
          "type": "hotspot",
          "settings": {
            "product": "ruffle-power-pareo-in-cotton-gauze",
            "variant_img": "shopify:\/\/shop_images\/CPB_S24_PoppyPurple_Pareo_Gauze.jpg",
            "hovertext": false,
            "tooltip_text": "Hover Text Here",
            "top": 15,
            "left": 62
          }
        },
        "hotspot_RbTEhb": {
          "type": "hotspot",
          "settings": {
            "product": "move-and-groove-pant",
            "variant_img": "shopify:\/\/shop_images\/CPB_MoveAndGroove.jpg",
            "hovertext": false,
            "tooltip_text": "Hover Text Here",
            "top": 47,
            "left": 78
          }
        }
      },
      "block_order": [
        "hotspot_HEJHDV",
        "hotspot_6JRnwK",
        "hotspot_RbTEhb"
      ],
      "settings": {
        "image": "https:\/\/cdn.shopify.com\/s\/files\/1\/0841\/0506\/8859\/files\/SpringDesktop1.png?v=1714013408",
        "hotspot_color": "#f47722",
        "hotspot_inner": "#ffffff",
        "icon": "",
        "width": 95
      }
    },
    "ticker_text_6frNjK": {
      "type": "ticker-text",
      "blocks": {
        "scroll_text_xq3A6T": {
          "type": "scroll-text",
          "settings": {
            "text": "Weather Report: As always, it's 77 and balmy at CPB"
          }
        },
        "scroll_text_68HYfL": {
          "type": "scroll-text",
          "settings": {
            "text": "FREE SIZE FOR THE FUTURE"
          }
        },
        "scroll_text_cyVCq3": {
          "type": "scroll-text",
          "settings": {
            "text": "Studio Number! 561-247-6334"
          }
        },
        "scroll_text_6FMfbc": {
          "type": "scroll-text",
          "settings": {
            "text": "Call the studio, just to chit chat"
          }
        },
        "scroll_text_hWQWhQ": {
          "type": "scroll-text",
          "settings": {
            "text": "Surf Report: Waves are double over head at Flagpole, but Reef is flat"
          }
        },
        "scroll_text_bezFna": {
          "type": "scroll-text",
          "settings": {
            "text": "Open Mon - Sat, 11 to 6(ish)"
          }
        },
        "scroll_text_zrJLiU": {
          "type": "scroll-text",
          "settings": {
            "text": "CONIGLIO MEANS RABBIT"
          }
        },
        "scroll_text_TtLQDp": {
          "type": "scroll-text",
          "settings": {
            "text": "561-247-6334"
          }
        },
        "scroll_text_qMLgeJ": {
          "type": "scroll-text",
          "settings": {
            "text": "It's made in India!"
          }
        },
        "scroll_text_4FiReG": {
          "type": "scroll-text",
          "settings": {
            "text": "Ruffle Power Pareo Forever"
          }
        },
        "scroll_text_JCBjxH": {
          "type": "scroll-text",
          "settings": {
            "text": "FREE SIZE BECAUSE IT MATTERS"
          }
        }
      },
      "block_order": [
        "scroll_text_xq3A6T",
        "scroll_text_68HYfL",
        "scroll_text_cyVCq3",
        "scroll_text_6FMfbc",
        "scroll_text_hWQWhQ",
        "scroll_text_bezFna",
        "scroll_text_zrJLiU",
        "scroll_text_TtLQDp",
        "scroll_text_qMLgeJ",
        "scroll_text_4FiReG",
        "scroll_text_JCBjxH"
      ],
      "custom_css": [

      ],
      "settings": {
        "text-size": 16,
        "text-color": "#312f2e",
        "background-color": "#f47722",
        "space": 6,
        "divider": "•",
        "height": 6
      }
    },
    "hotspot_section_Fx33je": {
      "type": "hotspot-section",
      "blocks": {
        "hotspot_iXGC3G": {
          "type": "hotspot",
          "settings": {
            "product": "beaded-party-top",
            "variant_img": "shopify:\/\/shop_images\/240422_Shot_18_0079.jpg",
            "hovertext": false,
            "tooltip_text": "Hover Text Here",
            "top": 21,
            "left": 71
          }
        },
        "hotspot_qEXwWd": {
          "type": "hotspot",
          "settings": {
            "product": "",
            "hovertext": false,
            "tooltip_text": "Hover Text Here",
            "top": 50,
            "left": 77
          }
        },
        "hotspot_CdcBWT": {
          "type": "hotspot",
          "settings": {
            "product": "",
            "hovertext": false,
            "tooltip_text": "Hover Text Here",
            "top": 76,
            "left": 77
          }
        },
        "hotspot_h9tmX8": {
          "type": "hotspot",
          "settings": {
            "product": "",
            "hovertext": false,
            "tooltip_text": "Hover Text Here",
            "top": 70,
            "left": 30
          }
        },
        "hotspot_6U6jrC": {
          "type": "hotspot",
          "settings": {
            "product": "",
            "hovertext": false,
            "tooltip_text": "Hover Text Here",
            "top": 80,
            "left": 26
          }
        },
        "hotspot_d8zHje": {
          "type": "hotspot",
          "settings": {
            "product": "",
            "hovertext": false,
            "tooltip_text": "Hover Text Here",
            "top": 73,
            "left": 12
          }
        }
      },
      "block_order": [
        "hotspot_iXGC3G",
        "hotspot_qEXwWd",
        "hotspot_CdcBWT",
        "hotspot_h9tmX8",
        "hotspot_6U6jrC",
        "hotspot_d8zHje"
      ],
      "settings": {
        "image": "https:\/\/cdn.shopify.com\/s\/files\/1\/0841\/0506\/8859\/files\/SpringDesktop2.png?v=1714013408",
        "hotspot_color": "#f47722",
        "hotspot_inner": "#ffffff",
        "icon": "",
        "width": 95
      }
    },
    "hotspot_section_VeBP8j": {
      "type": "hotspot-section",
      "blocks": {
        "hotspot_cwqkr4": {
          "type": "hotspot",
          "settings": {
            "product": "",
            "hovertext": false,
            "tooltip_text": "Hover Text Here",
            "top": 44,
            "left": 23
          }
        },
        "hotspot_HhtQhG": {
          "type": "hotspot",
          "settings": {
            "product": "",
            "hovertext": false,
            "tooltip_text": "Hover Text Here",
            "top": 41,
            "left": 89
          }
        },
        "hotspot_iWWH3k": {
          "type": "hotspot",
          "settings": {
            "product": "",
            "hovertext": false,
            "tooltip_text": "Hover Text Here",
            "top": 66,
            "left": 25
          }
        },
        "hotspot_9g9zVY": {
          "type": "hotspot",
          "settings": {
            "product": "",
            "hovertext": false,
            "tooltip_text": "Hover Text Here",
            "top": 75,
            "left": 60
          }
        }
      },
      "block_order": [
        "hotspot_cwqkr4",
        "hotspot_HhtQhG",
        "hotspot_iWWH3k",
        "hotspot_9g9zVY"
      ],
      "settings": {
        "image": "https:\/\/cdn.shopify.com\/s\/files\/1\/0841\/0506\/8859\/files\/SpringDEsktop3.png?v=1714013410",
        "hotspot_color": "#f47722",
        "hotspot_inner": "#ffffff",
        "icon": "",
        "width": 95
      }
    }
  },
  "order": [
    "custom_liquid_h6prJp",
    "hotspot_section_4EmjLw",
    "ticker_text_6frNjK",
    "hotspot_section_Fx33je",
    "hotspot_section_VeBP8j"
  ]
}
